{
    "one_red": [
        {"id": 1, "left": 300, "top": 40, "paddingLeft": 35, "paddingRight": 100, "padding": 80, "name": "inside"},
        {"id": 2, "left": 300, "top": 210, "paddingRight": 25, "padding": 118, "name": "middle"},
        {"id": 3, "left": 200, "top": 450, "paddingLeft": 150, "paddingRight": 180, "padding": 70, "name": "outside"}
    ],
    "two_red": [
        {"id": 1, "left": 156, "top": 420, "paddingLeft": 35, "paddingRight": 100, "padding": 110, "name": "inside"},
        {"id": 2, "left": 156, "top": 180, "paddingRight": 25, "padding": 118, "name": "middle"},
        {"id": 3, "left": 66, "top": 35, "paddingLeft": 150, "paddingRight": 180, "padding": 70, "name": "outside"}
    ],
    "one_blue": [
        {"id": 1, "left": 305, "top": 454,"paddingLeft": 35, "paddingRight": 100, "padding": 80, "name": "inside"},
        {"id": 2, "left": 305, "top": 215, "paddingRight": 25, "padding": 114, "name": "middle"},
        {"id": 3, "left": 190, "top": 75, "paddingLeft": 150, "paddingRight": 180, "padding": 67, "name": "outside"}
    ],
    "two_blue": [
        {"id": 1, "left": 105, "top": 100, "paddingRight": 113, "padding": 62, "name": "inside"},
        {"id": 2, "left": 105, "top": 230, "paddingRight": 25, "padding": 115, "name": "middle"},
        {"id": 3, "left": 105, "top": 465, "paddingLeft": 150, "paddingRight": 175, "padding": 70, "name": "outside"}
    ]
}